{
    "type": "create:mixing",
    "ingredients": [
        {
            "type": "fluid_tag",
            "amount": 250,
            "fluid_tag": "c:sour_cream"
        },
        {
            "item": "createfood:cream_cheese"
        },
        {
            "item": "createfood:cream_cheese"
        },
        {
            "item": "createfood:cream_cheese"
        },
        {
            "tag": "c:sugar"
        },
        {
            "tag": "c:salt"
        },
        {
            "tag": "c:eggs"
        },
        {
            "tag": "c:eggs"
        }
    ],
    "results": [
        {
            "amount": 1000,
            "id": "createfood:cheesecake_filling"
        }
    ]
}