{
    "neoforge:conditions": [
        {
            "type": "neoforge:not",
            "value": {
                "type": "neoforge:tag_empty",
                "tag": "c:dusts/cinnamon"
            }
        }
    ],
    "type": "minecraft:crafting_shapeless",
    "ingredients": [
        {
            "item": "minecraft:wheat"
        },
        {
            "tag": "c:sugar"
        },
        {
            "tag": "c:eggs"
        },
        {
            "tag": "c:dusts/cinnamon"
        }
    ],
    "result": {
        "count": 8,
        "id": "createfood:raw_snickerdoodle"
    }
}